autohyp/__init__.py
autohyp/module.py
autohyp-0.0.2.dist-info/LICENSE
autohyp-0.0.2.dist-info/METADATA
autohyp-0.0.2.dist-info/WHEEL
autohyp-0.0.2.dist-info/top_level.txt
autohyp-0.0.2.dist-info/RECORD
