Metadata-Version: 2.1
Name: autohyp
Version: 0.0.2
Summary: A simple hypothesis testing package
Home-page: https://github.com/Gabriel-Aspen/autohyp
Author: Gabriel Nager
Author-email: gabenager@gmail.com.com
License: UNKNOWN
Platform: UNKNOWN
Classifier: Programming Language :: Python :: 3
Classifier: License :: OSI Approved :: MIT License
Classifier: Operating System :: OS Independent
Requires-Python: >=3.6
License-File: LICENSE
